arbol/__init__.py
arbol/arbol.py
arbol/demo/__init__.py
arbol/demo/demo.py
arbol/tests/__init__.py
arbol/tests/test_arbol.py
arbol-2025.3.3.dist-info/METADATA
arbol-2025.3.3.dist-info/WHEEL
arbol-2025.3.3.dist-info/licenses/LICENSE
arbol-2025.3.3.dist-info/RECORD
