Metadata-Version: 2.4
Name: arbol
Version: 2025.3.3
Summary: arbol -- Arborescent Printouts in Python
Project-URL: Homepage, https://github.com/royerlab/arbol
Project-URL: Issues, https://github.com/royerlab/arbol/issues
Author-email: "Loic A. Royer" <loic.royer@czbiohub.org>
License-Expression: MIT
License-File: LICENSE
Keywords: console,logging,print,terminal,tree
Classifier: Operating System :: OS Independent
Classifier: Programming Language :: Python :: 3
Requires-Python: >=3.8
